[
    {
        "colo": "Default",
        "ip": "2606:4700:3019:19aa:ba6a:5905:3c69:9ad3",
        "latency": 1,
        "line": "CM",
        "loss": 0,
        "node": "WEBH",
        "speed": 310,
        "time": "2024-12-30 09:54:47"
    },
    {
        "colo": "Default",
        "ip": "2606:4700:3019:457f:1ccf:f82a:2ff7:90d8",
        "latency": 1,
        "line": "CM",
        "loss": 0,
        "node": "WEBH",
        "speed": 309,
        "time": "2024-12-30 09:54:46"
    },
    {
        "colo": "Default",
        "ip": "2606:4700:3019:318:c3:5ece:464b:126b",
        "latency": 1,
        "line": "CM",
        "loss": 0,
        "node": "WEBH",
        "speed": 309,
        "time": "2024-12-30 09:54:46"
    },
    {
        "colo": "Default",
        "ip": "2606:4700:3019:b971:b63:2137:a625:ab0",
        "latency": 1,
        "line": "CM",
        "loss": 0,
        "node": "WEBH",
        "speed": 308,
        "time": "2024-12-30 09:54:46"
    },
    {
        "colo": "Default",
        "ip": "2606:4700:3019:56b:6948:a07:2f60:1b0f",
        "latency": 1,
        "line": "CM",
        "loss": 0,
        "node": "WEBH",
        "speed": 307,
        "time": "2024-12-30 09:54:46"
    },
    {
        "colo": "Default",
        "ip": "2606:4700:3019:19aa:ba6a:5905:3c69:9ad3",
        "latency": 1,
        "line": "CT",
        "loss": 0,
        "node": "WEBH",
        "speed": 310,
        "time": "2024-12-30 09:54:47"
    },
    {
        "colo": "Default",
        "ip": "2606:4700:3019:457f:1ccf:f82a:2ff7:90d8",
        "latency": 1,
        "line": "CT",
        "loss": 0,
        "node": "WEBH",
        "speed": 309,
        "time": "2024-12-30 09:54:46"
    },
    {
        "colo": "Default",
        "ip": "2606:4700:3019:318:c3:5ece:464b:126b",
        "latency": 1,
        "line": "CT",
        "loss": 0,
        "node": "WEBH",
        "speed": 309,
        "time": "2024-12-30 09:54:46"
    },
    {
        "colo": "Default",
        "ip": "2606:4700:3019:b971:b63:2137:a625:ab0",
        "latency": 1,
        "line": "CT",
        "loss": 0,
        "node": "WEBH",
        "speed": 308,
        "time": "2024-12-30 09:54:46"
    },
    {
        "colo": "Default",
        "ip": "2606:4700:3019:56b:6948:a07:2f60:1b0f",
        "latency": 1,
        "line": "CT",
        "loss": 0,
        "node": "WEBH",
        "speed": 307,
        "time": "2024-12-30 09:54:46"
    },
    {
        "colo": "Default",
        "ip": "2606:4700:3019:19aa:ba6a:5905:3c69:9ad3",
        "latency": 1,
        "line": "CU",
        "loss": 0,
        "node": "WEBH",
        "speed": 310,
        "time": "2024-12-30 09:54:47"
    },
    {
        "colo": "Default",
        "ip": "2606:4700:3019:457f:1ccf:f82a:2ff7:90d8",
        "latency": 1,
        "line": "CU",
        "loss": 0,
        "node": "WEBH",
        "speed": 309,
        "time": "2024-12-30 09:54:46"
    },
    {
        "colo": "Default",
        "ip": "2606:4700:3019:318:c3:5ece:464b:126b",
        "latency": 1,
        "line": "CU",
        "loss": 0,
        "node": "WEBH",
        "speed": 309,
        "time": "2024-12-30 09:54:46"
    },
    {
        "colo": "Default",
        "ip": "2606:4700:3019:b971:b63:2137:a625:ab0",
        "latency": 1,
        "line": "CU",
        "loss": 0,
        "node": "WEBH",
        "speed": 308,
        "time": "2024-12-30 09:54:46"
    },
    {
        "colo": "Default",
        "ip": "2606:4700:3019:56b:6948:a07:2f60:1b0f",
        "latency": 1,
        "line": "CU",
        "loss": 0,
        "node": "WEBH",
        "speed": 307,
        "time": "2024-12-30 09:54:46"
    }
]