[
    {
        "colo": "Default",
        "ip": "2606:4700:9b02:4226:4aea:5047:13dc:9a77",
        "latency": 23,
        "line": "CM",
        "loss": 0,
        "node": "WEBH",
        "speed": 310,
        "time": "2025-01-14 20:44:36"
    },
    {
        "colo": "Default",
        "ip": "2606:4700:9b02:13a4:121a:40b8:5398:19c2",
        "latency": 22,
        "line": "CM",
        "loss": 0,
        "node": "WEBH",
        "speed": 308,
        "time": "2025-01-14 20:44:35"
    },
    {
        "colo": "Default",
        "ip": "2606:4700:9b02:7523:241f:c17:ef9:e9e7",
        "latency": 24,
        "line": "CM",
        "loss": 0,
        "node": "WEBH",
        "speed": 307,
        "time": "2025-01-14 20:44:35"
    },
    {
        "colo": "Default",
        "ip": "2606:4700:9b02:72e3:be83:2459:e1b6:7316",
        "latency": 20,
        "line": "CM",
        "loss": 0,
        "node": "WEBH",
        "speed": 307,
        "time": "2025-01-14 20:44:35"
    },
    {
        "colo": "Default",
        "ip": "2606:4700:9b02:ed2f:f46e:1251:1ba4:7012",
        "latency": 20,
        "line": "CM",
        "loss": 0,
        "node": "WEBH",
        "speed": 307,
        "time": "2025-01-14 20:44:35"
    },
    {
        "colo": "Default",
        "ip": "2606:4700:9b02:4226:4aea:5047:13dc:9a77",
        "latency": 23,
        "line": "CT",
        "loss": 0,
        "node": "WEBH",
        "speed": 310,
        "time": "2025-01-14 20:44:36"
    },
    {
        "colo": "Default",
        "ip": "2606:4700:9b02:13a4:121a:40b8:5398:19c2",
        "latency": 22,
        "line": "CT",
        "loss": 0,
        "node": "WEBH",
        "speed": 308,
        "time": "2025-01-14 20:44:35"
    },
    {
        "colo": "Default",
        "ip": "2606:4700:9b02:7523:241f:c17:ef9:e9e7",
        "latency": 24,
        "line": "CT",
        "loss": 0,
        "node": "WEBH",
        "speed": 307,
        "time": "2025-01-14 20:44:35"
    },
    {
        "colo": "Default",
        "ip": "2606:4700:9b02:72e3:be83:2459:e1b6:7316",
        "latency": 20,
        "line": "CT",
        "loss": 0,
        "node": "WEBH",
        "speed": 307,
        "time": "2025-01-14 20:44:35"
    },
    {
        "colo": "Default",
        "ip": "2606:4700:9b02:ed2f:f46e:1251:1ba4:7012",
        "latency": 20,
        "line": "CT",
        "loss": 0,
        "node": "WEBH",
        "speed": 307,
        "time": "2025-01-14 20:44:35"
    },
    {
        "colo": "Default",
        "ip": "2606:4700:9b02:4226:4aea:5047:13dc:9a77",
        "latency": 23,
        "line": "CU",
        "loss": 0,
        "node": "WEBH",
        "speed": 310,
        "time": "2025-01-14 20:44:36"
    },
    {
        "colo": "Default",
        "ip": "2606:4700:9b02:13a4:121a:40b8:5398:19c2",
        "latency": 22,
        "line": "CU",
        "loss": 0,
        "node": "WEBH",
        "speed": 308,
        "time": "2025-01-14 20:44:35"
    },
    {
        "colo": "Default",
        "ip": "2606:4700:9b02:7523:241f:c17:ef9:e9e7",
        "latency": 24,
        "line": "CU",
        "loss": 0,
        "node": "WEBH",
        "speed": 307,
        "time": "2025-01-14 20:44:35"
    },
    {
        "colo": "Default",
        "ip": "2606:4700:9b02:72e3:be83:2459:e1b6:7316",
        "latency": 20,
        "line": "CU",
        "loss": 0,
        "node": "WEBH",
        "speed": 307,
        "time": "2025-01-14 20:44:35"
    },
    {
        "colo": "Default",
        "ip": "2606:4700:9b02:ed2f:f46e:1251:1ba4:7012",
        "latency": 20,
        "line": "CU",
        "loss": 0,
        "node": "WEBH",
        "speed": 307,
        "time": "2025-01-14 20:44:35"
    }
]