[
    {
        "colo": "Default",
        "ip": "2606:4700:90c3:fe2a:7fd2:ccd9:26a4:f56f",
        "latency": 24,
        "line": "CM",
        "loss": 0,
        "node": "WEBH",
        "speed": 310,
        "time": "2025-03-27 13:26:15"
    },
    {
        "colo": "Default",
        "ip": "2606:4700:8ca4:d27:bdcd:268c:e041:15be",
        "latency": 20,
        "line": "CM",
        "loss": 0,
        "node": "WEBH",
        "speed": 310,
        "time": "2025-03-27 13:26:16"
    },
    {
        "colo": "Default",
        "ip": "2606:4700:8ca4:86ed:7534:8b43:2f13:a299",
        "latency": 19,
        "line": "CM",
        "loss": 0,
        "node": "WEBH",
        "speed": 309,
        "time": "2025-03-27 13:26:15"
    },
    {
        "colo": "Default",
        "ip": "2606:4700:90c3:d10c:f2bc:f715:f843:d839",
        "latency": 20,
        "line": "CM",
        "loss": 0,
        "node": "WEBH",
        "speed": 308,
        "time": "2025-03-27 13:26:17"
    },
    {
        "colo": "Default",
        "ip": "2606:4700:90c3:dcc6:b55e:fb7d:f0db:e9e1",
        "latency": 22,
        "line": "CM",
        "loss": 0,
        "node": "WEBH",
        "speed": 307,
        "time": "2025-03-27 13:26:17"
    },
    {
        "colo": "Default",
        "ip": "2606:4700:90c3:fe2a:7fd2:ccd9:26a4:f56f",
        "latency": 24,
        "line": "CT",
        "loss": 0,
        "node": "WEBH",
        "speed": 310,
        "time": "2025-03-27 13:26:15"
    },
    {
        "colo": "Default",
        "ip": "2606:4700:8ca4:d27:bdcd:268c:e041:15be",
        "latency": 20,
        "line": "CT",
        "loss": 0,
        "node": "WEBH",
        "speed": 310,
        "time": "2025-03-27 13:26:16"
    },
    {
        "colo": "Default",
        "ip": "2606:4700:8ca4:86ed:7534:8b43:2f13:a299",
        "latency": 19,
        "line": "CT",
        "loss": 0,
        "node": "WEBH",
        "speed": 309,
        "time": "2025-03-27 13:26:15"
    },
    {
        "colo": "Default",
        "ip": "2606:4700:90c3:d10c:f2bc:f715:f843:d839",
        "latency": 20,
        "line": "CT",
        "loss": 0,
        "node": "WEBH",
        "speed": 308,
        "time": "2025-03-27 13:26:17"
    },
    {
        "colo": "Default",
        "ip": "2606:4700:90c3:dcc6:b55e:fb7d:f0db:e9e1",
        "latency": 22,
        "line": "CT",
        "loss": 0,
        "node": "WEBH",
        "speed": 307,
        "time": "2025-03-27 13:26:17"
    },
    {
        "colo": "Default",
        "ip": "2606:4700:90c3:fe2a:7fd2:ccd9:26a4:f56f",
        "latency": 24,
        "line": "CU",
        "loss": 0,
        "node": "WEBH",
        "speed": 310,
        "time": "2025-03-27 13:26:15"
    },
    {
        "colo": "Default",
        "ip": "2606:4700:8ca4:d27:bdcd:268c:e041:15be",
        "latency": 20,
        "line": "CU",
        "loss": 0,
        "node": "WEBH",
        "speed": 310,
        "time": "2025-03-27 13:26:16"
    },
    {
        "colo": "Default",
        "ip": "2606:4700:8ca4:86ed:7534:8b43:2f13:a299",
        "latency": 19,
        "line": "CU",
        "loss": 0,
        "node": "WEBH",
        "speed": 309,
        "time": "2025-03-27 13:26:15"
    },
    {
        "colo": "Default",
        "ip": "2606:4700:90c3:d10c:f2bc:f715:f843:d839",
        "latency": 20,
        "line": "CU",
        "loss": 0,
        "node": "WEBH",
        "speed": 308,
        "time": "2025-03-27 13:26:17"
    },
    {
        "colo": "Default",
        "ip": "2606:4700:90c3:dcc6:b55e:fb7d:f0db:e9e1",
        "latency": 22,
        "line": "CU",
        "loss": 0,
        "node": "WEBH",
        "speed": 307,
        "time": "2025-03-27 13:26:17"
    }
]